py_package/__init__.py
py_package/__main__.py
py_package/calculation.py
py_package/tests/__init__.py
py_package/tests/test_calculation.py
pymvil/__init__.py
pymvil/__main__.py
pymvil/create_visualizations.py
pymvil/mvil.py
pymvil/no_monotonic_trend_analysis.py
pymvil/save_result_as_csv.py
pymvil/tests/__init__.py
pymvil/tests/test_mvil_csv_3_variables.py
pymvil/tests/test_mvil_csv_n_dependent_variables.py
pymvil/tests/test_mvil_csv_n_independent_variables_monotonic_trend.py
pymvil/tests/test_mvil_csv_no_monotonic_trend.py
pymvil/tests/test_mvil_np_array.py
pymvil-0.0.1.dist-info/LICENSE
pymvil-0.0.1.dist-info/METADATA
pymvil-0.0.1.dist-info/WHEEL
pymvil-0.0.1.dist-info/entry_points.txt
pymvil-0.0.1.dist-info/top_level.txt
pymvil-0.0.1.dist-info/RECORD
